infosrv_llm_observe/__init__.py
infosrv_llm_observe/client.py
infosrv_llm_observe/decorators.py
infosrv_llm_observe/exceptions.py
infosrv_llm_observe/instrument.py
infosrv_llm_observe/registry.py
infosrv_llm_observe/utils.py
infosrv_llm_observe/version.py
infosrv_llm_observe-0.1.4.dist-info/licenses/LICENSE
infosrv_llm_observe-0.1.4.dist-info/METADATA
infosrv_llm_observe-0.1.4.dist-info/WHEEL
infosrv_llm_observe-0.1.4.dist-info/top_level.txt
infosrv_llm_observe-0.1.4.dist-info/RECORD
